MANIFEST.in
README.rst
setup.py
tpow/__init__.py
tpow/device.py
tpow/sensor.py
tpow/usb9097.py
tpow.egg-info/PKG-INFO
tpow.egg-info/SOURCES.txt
tpow.egg-info/dependency_links.txt
tpow.egg-info/requires.txt
tpow.egg-info/top_level.txt
tpow/examples/00readme.txt
tpow/examples/01testlog.txt
tpow/examples/cfg.py
tpow/examples/check_ds18b20_matchrom.py
tpow/examples/check_ds18b20_skiprom.py
tpow/examples/check_ds2438_matchrom.py
tpow/examples/check_ds2438_skiprom.py
tpow/examples/check_read_rom.py
tpow/examples/check_search_roms.py