Metadata-Version: 1.1
Name: tpow
Version: 0.2.0
Summary: Tiny 1-wire utility. 100% pure python, USB9097 specific.
Home-page: https://github.com/sken10/tpow
Author: Kenichi SHIRAKAWA
Author-email: shirakawa.kenichi@gmail.com
License: MIT License
Keywords: 1-wire one-wire USB humidity temperature DS2480 DS18B20 DS2438
Platform: UNKNOWN
Classifier: Development Status :: 2 - Pre-Alpha
Classifier: Programming Language :: Python
Classifier: Topic :: Software Development :: Libraries
Classifier: Topic :: System :: Hardware :: Hardware Drivers
